{"skeleton":{"hash":"VvQh36IMiK80qArAUra7os4UzXo","spine":"3.8.75","x":0.56,"y":-191.2,"width":98.14,"height":134.88,"images":"","audio":""},"bones":[{"name":"root","x":35.72,"y":-94.83},{"name":"bone","parent":"root","length":79.87,"rotation":-68.63,"x":0.15,"y":-0.23}],"slots":[{"name":"thighL","bone":"bone","attachment":"thighLHolder"}],"skins":[{"name":"0","attachments":{"thighL":{"thighLHolder":{"name":"thigh","x":40.16,"y":6.24,"rotation":84.7,"width":65,"height":121}}}},{"name":"1","attachments":{"thighL":{"thighLHolder":{"name":"thigh2","x":31.74,"y":2.37,"rotation":85.99,"width":65,"height":121}}}}],"animations":{"450":{"bones":{"bone":{"rotate":[{},{"time":0.3333,"angle":-22.69,"curve":"stepped"},{"time":0.5,"angle":-22.69},{"time":0.8333,"angle":-12.23},{"time":1,"angle":-98.02},{"time":1.1667,"angle":167.69},{"time":1.3333,"angle":60.51},{"time":1.5,"angle":-54.35},{"time":1.6667,"angle":-101.49}]},"root":{"translate":[{"time":0.5},{"time":0.6333,"x":27.28,"y":39.97},{"time":0.8333,"x":112.97,"y":70.07},{"time":0.9,"x":113.74,"y":119.92},{"time":1,"x":180.73,"y":120.89},{"time":1.1667,"x":182.16,"y":143.48},{"time":1.3333,"x":157,"y":89.13},{"time":1.6667,"x":137.11,"y":93.81}],"shear":[{"time":1.8333}]}}},"hurricanrana":{"bones":{"root":{"translate":[{},{"time":0.3333,"x":39.06,"y":48.32},{"time":0.5,"x":34.95,"y":43.18},{"time":0.7667,"x":41.59,"y":34.94},{"time":0.8,"x":30.3,"y":19.8},{"time":0.8333,"x":26.03,"y":4.23},{"time":0.8667,"x":9.19,"y":-2.51},{"time":1,"x":-14.18,"y":-137.43}]},"bone":{"rotate":[{},{"time":0.3333,"angle":52.95},{"time":0.5,"angle":55.21},{"time":0.8333,"angle":129.71},{"time":1,"angle":-98.97}]}}},"idle1":{"bones":{"root":{"translate":[{},{"time":0.6667,"y":-22.39},{"time":1.3333}]},"bone":{"rotate":[{},{"time":0.6667,"angle":9.13},{"time":1.3333}]}}},"idleGround1":{"bones":{"bone":{"rotate":[{"angle":62.43}]},"root":{"translate":[{"x":6.63,"y":67.68}]}}},"idleGround2":{"bones":{"bone":{"rotate":[{"angle":-20.73}]}}},"sell2":{"bones":{"bone":{"rotate":[{},{"time":0.3333,"angle":-24.57,"curve":"stepped"},{"time":0.5,"angle":-24.57},{"time":0.6667,"angle":-74.55},{"time":0.8333,"angle":122.48},{"time":0.9,"angle":63.33}]},"root":{"translate":[{"time":0.5},{"time":0.6667,"x":79.5,"y":133.95},{"time":0.7667,"x":174.02,"y":34.63},{"time":0.8333,"x":251.56,"y":-80.59},{"time":0.9,"x":259.89,"y":-109.15}]}}},"superkick":{"bones":{"root":{"translate":[{},{"time":0.0333,"x":-17.48,"y":-7.2},{"time":0.0667,"x":-9.25,"y":33.92},{"time":0.1,"x":-8.22,"y":4.11},{"time":0.1667,"x":20.56,"y":38.04},{"time":0.2667,"x":49.34,"y":22.62,"curve":"stepped"},{"time":0.5,"x":49.34,"y":22.62},{"time":0.5333,"x":25.08,"y":39.68},{"time":0.5667,"x":3.39,"y":41.07},{"time":0.6,"x":-0.82,"y":112.7},{"time":0.6333,"x":2.67,"y":-11.5},{"time":0.6667}],"shear":[{},{"time":0.1,"x":-180,"curve":"stepped"},{"time":0.5,"x":-180},{"time":0.6667}]},"bone":{"rotate":[{},{"time":0.1,"angle":-21.39},{"time":0.1667,"angle":-123.66,"curve":"stepped"},{"time":0.5,"angle":-123.66},{"time":0.6667}]}}},"walk1":{"bones":{"bone":{"rotate":[{"angle":2.95},{"time":0.3333,"angle":-44.62},{"time":0.8333,"angle":17.2},{"time":1,"angle":2.95}]}}}}}